Metadata-Version: 2.1
Name: tasklib
Version: 2.5.1
Summary: Official Taskwarrior library for Python
Home-page: https://github.com/GothenburgBitFactory/tasklib
Download-URL: https://github.com/GothenburgBitFactory/tasklib/downloads
Author: GothenburgBitFactory
Author-email: support@gothenburgbitfactory.org
License: BSD
Classifier: Development Status :: 6 - Mature
Classifier: Programming Language :: Python
Classifier: Programming Language :: Python :: 3
Classifier: Programming Language :: Python :: 3.5
Classifier: Programming Language :: Python :: 3.6
Classifier: Programming Language :: Python :: 3.7
Classifier: Programming Language :: Python :: 3.8
Classifier: Programming Language :: Python :: 3.9
Classifier: Programming Language :: Python :: 3.10
Classifier: License :: OSI Approved :: BSD License
Classifier: Topic :: Software Development :: Libraries :: Python Modules
Classifier: Intended Audience :: Developers
Classifier: Intended Audience :: Information Technology
Classifier: Intended Audience :: System Administrators
Classifier: Operating System :: OS Independent
License-File: LICENSE
License-File: AUTHORS
